src/__init__.py
src/getlinks.py
src/webscrape.py
webbyApp-0.1.dist-info/DESCRIPTION.rst
webbyApp-0.1.dist-info/METADATA
webbyApp-0.1.dist-info/RECORD
webbyApp-0.1.dist-info/WHEEL
webbyApp-0.1.dist-info/metadata.json
webbyApp-0.1.dist-info/top_level.txt
