Metadata-Version: 2.0
Name: webbyApp
Version: 0.1
Summary: The funniest joke in the world
Home-page: https://github.com/maltaweel/webbyApp.git
Author: Mark Altaweel
Author-email: markaltaweel@example.com
License: MIT
Platform: UNKNOWN
Requires-Python: >=2.7
Requires-Dist: beautifulsoup4
